setup.py
damemysql/__init__.py
damemysql.egg-info/PKG-INFO
damemysql.egg-info/SOURCES.txt
damemysql.egg-info/dependency_links.txt
damemysql.egg-info/not-zip-safe
damemysql.egg-info/requires.txt
damemysql.egg-info/top_level.txt
damemysql/files/__init__.py
damemysql/files/data.pickle
damemysql/tests/__init__.py
damemysql/tests/test_basics.py
damemysql/tests/test_basics.py~
damemysql/tests/test_maths.py
damemysql/tests/__pycache__/test_basics.cpython-35.pyc
damemysql/tests/__pycache__/test_maths.cpython-35.pyc