Metadata-Version: 1.1
Name: damemysql
Version: 0.0.16
Summary: Learning about MYSQL from tests
Home-page: http://github.com/davidam/damemysql
Author: David Arroyo Menéndez
Author-email: davidam@gnu.org
License: GPLv3
Keywords: sql mysql
Platform: UNKNOWN
Classifier: Development Status :: 3 - Alpha
Classifier: License :: OSI Approved :: GNU General Public License v3 (GPLv3)
Classifier: Programming Language :: Python :: 3.6
Classifier: Topic :: Text Processing :: Linguistic
